{"Lat":0,"Long":0,"Date":"2019-07-05T15:33:13-03:00","Orientation":1,"Exif":{"ApertureValue":2.200000058737805,"BrightnessValue|*imagemeta.rat[int32]":"1331/898","ComponentsConfiguration":"1 2 3 0","CreateDate":"2019:07:05 15:33:13","DateTimeOriginal":"2019:07:05 15:33:13","ExposureCompensation|*imagemeta.rat[int32]":"0","ExposureTime|*imagemeta.rat[uint32]":"1/30","FNumber|*imagemeta.rat[uint32]":"11/5","FocalLengthIn35mmFormat|uint16":"29","FocalLength|*imagemeta.rat[uint32]":"83/20","ISO|uint16":"200","LensInfo":"4.15 4.15 2.2 2.2","LensMake":"Apple","LensModel":"iPhone 6 back camera 4.15mm f/2.2","Make":"Apple","MakerNoteApple":"Apple iOSMM.ïŋ―hïŋ―ïŋ―ïŋ―Rbplist00Oïŋ―ïŋ―ïŋ―ïŋ―ïŋ―m_TJA?;\u003c?9lowïŋ―ïŋ―ïŋ―ïŋ―wdYUUaLaxz}ïŋ―ïŋ―ïŋ―ïŋ―ïŋ―ïŋ―}sv|qïŋ―ïŋ―ïŋ―ïŋ―ïŋ―ïŋ―ïŋ―ïŋ―ïŋ―ïŋ―ïŋ―ïŋ―ïŋ―ïŋ―ïŋ―B[ïŋ―mïŋ―ïŋ―ïŋ―ïŋ―\u003cBïŋ―ïŋ―ïŋ―ïŋ―B@9ïŋ―ïŋ―ïŋ―_ïŋ―ïŋ―ïŋ―ïŋ―Qïŋ―ïŋ―ïŋ―ïŋ―ïŋ―zïŋ―4ïŋ―Hïŋ―ïŋ―!#ïŋ―ïŋ―ïŋ―ïŋ―ïŋ―ïŋ―ïŋ―ïŋ―ïŋ―mïŋ―ïŋ―_ïŋ―ïŋ―[ïŋ―t0%$-ïŋ―B+\u003ef)(Zb'\u0026)(\"+2Z\"8=ïŋ―B)$87tn]L[aJ3 ïŋ―f%jïŋ―Rïŋ―ïŋ―ïŋ―rUK$-AWA8^ïŋ―]ïŋ―ïŋ―ïŋ―ïŋ―`Y'1+=PNI{ïŋ―plwïŋ―Eïŋ―v?NGNflgyïŋ―fifïŋ―ïŋ―ïŋ―jPY_vïŋ―ïŋ―ïŋ―ïŋ―jflïŋ―ïŋ―ïŋ―ïŋ―bplist00ïŋ―UflagsUvalueYtimescaleUepochïŋ―ïŋ―wïŋ―\u003eF;ïŋ―ïŋ―'-/8=?ïŋ―ïŋ―ïŋ―ïŋ―1ïŋ―ïŋ―ïŋ―ïŋ―ïŋ―ïŋ―ïŋ―Ũ","Model":"iPhone 6","ModifyDate":"2019:07:05 15:33:13","Orientation|uint16":"1","SceneCaptureType|uint16":"0","SceneType|uint8":"1","ShutterSpeedValue":0.033316008175590474,"Software":"11.4.1","SubSecTimeDigitized|int":"486","SubSecTimeOriginal|int":"486","SubjectArea":"1631 1223 1795 1077","YCbCrPositioning|uint16":"1"},"IPTC":{},"XMP":{}}
